nftopt/__init__.py
nftopt/nft.py
nftopt-0.0.1.dist-info/METADATA
nftopt-0.0.1.dist-info/RECORD
nftopt-0.0.1.dist-info/WHEEL
nftopt-0.0.1.dist-info/top_level.txt
