Metadata-Version: 2.1
Name: nftopt
Version: 0.0.1
Summary: Nakanishi-Fujii-Todo method for scipy.optimize
Home-page: https://github.com/ken-nakanishi/nftopt
Author: Ken Nakanishi
Author-email: ikyhn1.ken.n@gmail.com
License: 
Requires-Dist: numpy
Requires-Dist: scipy
